bmtrain/C.cpython-311-x86_64-linux-gnu.so
bmtrain/__init__.py
bmtrain/block_layer.py
bmtrain/debug.py
bmtrain/global_var.py
bmtrain/hook_func.py
bmtrain/init.py
bmtrain/layer.py
bmtrain/param_init.py
bmtrain/parameter.py
bmtrain/pipe_layer.py
bmtrain/store.py
bmtrain/synchronize.py
bmtrain/utils.py
bmtrain/wrapper.py
bmtrain/zero_context.py
bmtrain/benchmark/__init__.py
bmtrain/benchmark/all_gather.py
bmtrain/benchmark/reduce_scatter.py
bmtrain/benchmark/send_recv.py
bmtrain/benchmark/shape.py
bmtrain/benchmark/utils.py
bmtrain/distributed/__init__.py
bmtrain/distributed/ops.py
bmtrain/inspect/__init__.py
bmtrain/inspect/format.py
bmtrain/inspect/model.py
bmtrain/inspect/tensor.py
bmtrain/loss/__init__.py
bmtrain/loss/_function.py
bmtrain/loss/cross_entropy.py
bmtrain/lr_scheduler/__init__.py
bmtrain/lr_scheduler/cosine.py
bmtrain/lr_scheduler/exponential.py
bmtrain/lr_scheduler/linear.py
bmtrain/lr_scheduler/no_decay.py
bmtrain/lr_scheduler/noam.py
bmtrain/lr_scheduler/warmup.py
bmtrain/nccl/__init__.py
bmtrain/nccl/enums.py
bmtrain/nn/__init__.py
bmtrain/nn/column_parallel_linear.py
bmtrain/nn/linear.py
bmtrain/nn/parallel_embedding.py
bmtrain/nn/parallel_linear_func.py
bmtrain/nn/row_parallel_linear.py
bmtrain/optim/__init__.py
bmtrain/optim/_distributed.py
bmtrain/optim/_function.py
bmtrain/optim/adam.py
bmtrain/optim/adam_offload.py
bmtrain/optim/optim_manager.py
bmtrain-1.0.1.dist-info/licenses/LICENSE
bmtrain-1.0.1.dist-info/METADATA
bmtrain-1.0.1.dist-info/WHEEL
bmtrain-1.0.1.dist-info/top_level.txt
bmtrain-1.0.1.dist-info/RECORD
